{"encodings":["src/components/organisms/Home/featureJobs/index.tsx","FeatureJobs",[14,20,70,1],[14,21,14,45],[16,40,16,51],[17,30,17,56],[17,10,17,14],[17,16,17,25],[19,34,19,59],[21,2,25,12],[25,6,25,10],[33,6,67,16],[34,8,57,23],[36,12,42,18],[38,16,40,22],[39,18,39,40],[44,12,55,18],[51,16,53,22],[52,18,52,39],[58,8,66,14],[59,10,65,12],"src/components/providers/MainProvider/MainProvider.tsx","MainProvider",[21,28,36,1],[21,29,21,48],[22,19,22,32],[25,4,34,26],[26,6,33,17],[27,8,32,22],[29,46,29,56],[31,10,31,32],"src/components/organisms/Home/companies/companies.tsx","Companies",[8,25,24,1],[9,30,9,50],[9,10,9,14],[9,16,9,25],[12,4,22,10],[14,6,21,8],[18,27,18,48],"src/components/providers/Header/index.tsx","Header",[61,15,160,1],[62,19,62,32],[63,23,63,38],[63,10,63,18],[64,15,64,64],[74,8,79,16],[76,19,76,51],[86,8,88,14],[86,52,86,68],[93,32,93,44],[94,52,94,67],[101,4,158,20],[102,6,111,13],[103,8,110,10],[112,6,118,8],[119,6,157,11],[122,12,130,25],[123,14,129,21],[128,16,128,56],[131,12,138,25],[132,14,137,21],[136,16,136,36],[142,12,149,25],[143,14,148,21],[150,12,154,23],[151,14,153,22],[152,16,152,32],"src/components/molecules/components/403/index.tsx","NoAccess",[6,15,25,1],[7,17,7,28],[14,4,23,6],[19,8,21,17],"src/components/molecules/components/swiperSlide/swiperSlider.tsx","SwiperSlider",[23,56,58,1],[23,57,23,62],[26,20,26,41],[30,6,37,13],[31,8,33,14],[31,22,31,58],[32,10,32,32],[34,8,36,14],[34,22,34,58],[35,10,35,33],[38,6,55,15],[49,10,53,16],[50,12,52,26]],"reactData":{"src/components/organisms/Home/featureJobs/index.tsx":{"components":{"FeatureJobs":{"loc":[14,20,70,1],"nameLoc":[14,6,14,17],"captures":[{"loc":[14,20,70,1],"kind":512},{"loc":[14,21,14,45],"kind":2},{"loc":[16,40,16,51],"kind":4},{"loc":[17,30,17,56],"kind":4},{"loc":[19,34,19,59],"kind":4},{"loc":[21,2,25,12],"kind":128},{"loc":[21,2,25,12],"kind":1},{"loc":[34,8,57,23],"kind":16},{"loc":[36,12,42,18],"kind":16},{"loc":[38,16,40,22],"kind":16},{"loc":[39,18,39,40],"kind":16},{"loc":[44,12,55,18],"kind":16},{"loc":[51,16,53,22],"kind":16},{"loc":[52,18,52,39],"kind":16},{"loc":[59,10,65,12],"kind":16}]}},"externals":[{"kind":"import","loc":[2,0,2,47]},{"kind":"import","loc":[3,0,3,39]},{"kind":"import","loc":[4,0,4,54]},{"kind":"import","loc":[5,0,5,51]},{"kind":"import","loc":[7,0,7,44]},{"kind":"import","loc":[8,0,8,40]},{"kind":"export","loc":[71,0,71,27]}]},"src/components/providers/MainProvider/MainProvider.tsx":{"components":{"MainProvider":{"loc":[21,28,36,1],"nameLoc":[21,13,21,25],"captures":[{"loc":[21,28,36,1],"kind":512},{"loc":[21,29,21,48],"kind":2},{"loc":[22,19,22,32],"kind":4},{"loc":[25,4,34,26],"kind":16},{"loc":[26,6,33,17],"kind":16},{"loc":[27,8,32,22],"kind":16},{"loc":[29,46,29,56],"kind":16},{"loc":[31,10,31,32],"kind":16}]}},"externals":[{"kind":"import","loc":[5,0,5,55]},{"kind":"import","loc":[6,0,6,73]},{"kind":"import","loc":[7,0,7,68]},{"kind":"import","loc":[8,0,8,46]},{"kind":"import","loc":[9,0,9,34]},{"kind":"import","loc":[10,0,10,39]},{"kind":"import","loc":[11,0,11,62]},{"kind":"import","loc":[13,0,13,31]},{"kind":"export","loc":[21,0,36,2]}]},"src/components/organisms/Home/companies/companies.tsx":{"components":{"Companies":{"loc":[8,25,24,1],"nameLoc":[8,13,8,22],"captures":[{"loc":[8,25,24,1],"kind":512},{"loc":[9,30,9,50],"kind":4},{"loc":[14,6,21,8],"kind":16},{"loc":[18,27,18,48],"kind":16}]}},"externals":[{"kind":"import","loc":[2,0,2,47]},{"kind":"import","loc":[4,0,4,65]},{"kind":"import","loc":[6,0,6,47]},{"kind":"export","loc":[8,0,24,2]}]},"src/components/providers/Header/index.tsx":{"components":{"Header":{"loc":[61,15,160,1],"nameLoc":[61,24,61,30],"captures":[{"loc":[61,15,160,1],"kind":512},{"loc":[62,19,62,32],"kind":4},{"loc":[63,23,63,38],"kind":4},{"loc":[64,15,64,64],"kind":4},{"loc":[76,19,76,51],"kind":128},{"loc":[86,52,86,68],"kind":128},{"loc":[93,32,93,44],"kind":4},{"loc":[94,52,94,67],"kind":4},{"loc":[101,4,158,20],"kind":16},{"loc":[103,8,110,10],"kind":16},{"loc":[112,6,118,8],"kind":16},{"loc":[122,12,130,25],"kind":16},{"loc":[128,16,128,56],"kind":16},{"loc":[131,12,138,25],"kind":16},{"loc":[142,12,149,25],"kind":16},{"loc":[150,12,154,23],"kind":16},{"loc":[151,14,153,22],"kind":16},{"loc":[152,16,152,32],"kind":16}]}},"externals":[{"kind":"import","loc":[5,0,5,57]},{"kind":"import","loc":[6,0,6,59]},{"kind":"import","loc":[7,0,7,49]},{"kind":"import","loc":[8,0,8,50]},{"kind":"import","loc":[9,0,9,31]},{"kind":"import","loc":[10,0,10,29]},{"kind":"import","loc":[11,0,11,33]},{"kind":"import","loc":[12,0,12,55]},{"kind":"import","loc":[14,0,14,58]},{"kind":"import","loc":[16,0,16,65]},{"kind":"export","loc":[61,0,160,1]}]},"src/components/molecules/components/403/index.tsx":{"components":{"NoAccess":{"loc":[6,15,25,1],"nameLoc":[6,24,6,32],"captures":[{"loc":[6,15,25,1],"kind":512},{"loc":[7,17,7,28],"kind":4},{"loc":[14,4,23,6],"kind":16},{"loc":[19,8,21,17],"kind":16}]}},"externals":[{"kind":"import","loc":[2,0,2,38]},{"kind":"import","loc":[3,0,3,44]},{"kind":"import","loc":[4,0,4,26]},{"kind":"export","loc":[6,0,25,1]}]},"src/components/molecules/components/swiperSlide/swiperSlider.tsx":{"components":{"SwiperSlider":{"loc":[23,56,58,1],"nameLoc":[23,13,23,53],"captures":[{"loc":[23,56,58,1],"kind":512},{"loc":[23,57,23,62],"kind":2},{"loc":[26,20,26,41],"kind":4},{"loc":[30,6,37,13],"kind":16},{"loc":[31,22,31,58],"kind":128},{"loc":[32,10,32,32],"kind":16},{"loc":[34,22,34,58],"kind":128},{"loc":[35,10,35,33],"kind":16},{"loc":[38,6,55,15],"kind":16},{"loc":[50,12,52,26],"kind":16}]}},"externals":[{"kind":"import","loc":[2,0,2,76]},{"kind":"import","loc":[3,0,3,28]},{"kind":"import","loc":[4,0,4,31]},{"kind":"import","loc":[5,0,5,20]},{"kind":"import","loc":[6,0,6,38]},{"kind":"import","loc":[7,0,7,33]},{"kind":"import","loc":[8,0,8,51]},{"kind":"import","loc":[9,0,9,20]},{"kind":"import","loc":[10,0,10,31]},{"kind":"import","loc":[11,0,11,31]},{"kind":"import","loc":[12,0,12,30]},{"kind":"export","loc":[23,0,58,2]}]}}}